Workbook

Sheet Premissas
B2: Zēllu — simulador de monetização
B3: Altere só as células amarelas. Todas as outras contas, na aba Cenários, se atualizam sozinhas.
B4: Premissas gerais
B5: Preço ao cliente (por colaborador/mês) | C5: 12 | D5: Quanto a empresa cliente paga por colaborador por mês.
B6: Custo variável (por colaborador/mês) | C6: 2 | D6: IA, servidor e banco de dados. Sobe se o chat com IA for muito usado.
B7: Impostos sobre o que você recebe | C7: 0.1 | D7: Estimativa de Simples Nacional para software. Confirme com um contador.
B8: Seus custos fixos mensais | C8: 0 | D8: Contador, ferramentas, domínio, jurídico. Deixei 0 para bater com a conversa; preencha o seu valor real.
B10: Modelo 1 — Epic como canal
B11: Percentual que fica com a Epic | C11: 0.25 | D11: Comissão ou participação da Epic sobre cada contrato que ela traz.
B13: Modelo 2 — Licença white-label
B14: Licença paga pela Epic (por colaborador/mês) | C14: 6 | D14: A Epic revende pelo preço que quiser e paga isto a você.
B15: Mínimo mensal garantido | C15: 5000 | D15: Valor mínimo que a Epic paga por mês, mesmo com poucos usuários.
B16: Taxa de implantação do white-label | C16: 25000 | D16: Paga uma única vez pela Epic, pela personalização com a marca dela.
B17: Taxa de implantação por cliente novo | C17: 0 | D17: Opcional: cobrada a cada novo cliente que a Epic ativar (configuração, treinamento do RH).
B18: Modelo 3 — Sociedade no produto
B19: Sua participação na empresa | C19: 0.5 | D19: Percentual da sociedade que fica com você.
B20: Múltiplo de avaliação mínimo | C20: 2 | D20: Quantas vezes a receita anual a empresa valeria (cenário conservador).
B21: Múltiplo de avaliação máximo | C21: 5 | D21: Quantas vezes a receita anual a empresa valeria (cenário otimista).
B23: Se a Epic quiser comprar o Zēllu
B24: Horas investidas no produto (mínimo) | C24: 800 | D24: Estimativa de horas para refazer o Zēllu do zero.
B25: Horas investidas no produto (máximo) | C25: 1500
B26: Valor da hora (mínimo) | C26: 100 | D26: Valor de mercado da hora de desenvolvimento.
B27: Valor da hora (máximo) | C27: 150
B28: Preço de venda — piso | C28: =C24*C26 | D28: Abaixo disso, a venda não paga nem o trabalho já feito.
B29: Preço de venda — referência alta | C29: =C25*C27 | D29: Ainda costuma ser menos que 1 a 2 anos do modelo de canal com 5 clientes.

Sheet Cenários
A1: Quanto sobra para você em cada modelo (valores líquidos, depois de impostos e custos)
A2: Edite as colunas amarelas (nome, clientes e colaboradores). As linhas 8 e 9 são livres para os seus próprios cenários.
A3: Cenário | D3: Modelo 1 — Epic como canal | F3: Modelo 2 — White-label | J3: Modelo 3 — Sociedade
A4: Nome | B4: Nº de clientes | C4: Colaboradores pagantes | D4: Seu líquido por mês | E4: Seu líquido por ano | F4: Seu líquido por mês | G4: Seu líquido por ano | H4: Implantações (líquido) | I4: Total no 1º ano | J4: Receita anual da empresa | K4: Sua parte do lucro (ano) | L4: Sua parte do valor (mín.) | M4: Sua parte do valor (máx.)
A5: Piloto (1 cliente) | B5: 1 | C5: 200 | D5: =IF(C5="","",C5*Premissas!$C$5*(1-Premissas!$C$11)*(1-Premissas!$C$7)-C5*Premissas!$C$6-Premissas!$C$8) | E5: =IF(D5="","",D5*12) | F5: =IF(C5="","",MAX(C5*Premissas!$C$14,Premissas!$C$15)*(1-Premissas!$C$7)-C5*Premissas!$C$6-Premissas!$C$8) | G5: =IF(F5="","",F5*12) | H5: =IF(B5="","",(Premissas!$C$16+B5*Premissas!$C$17)*(1-Premissas!$C$7)) | I5: =IF(OR(G5="",H5=""),"",G5+H5) | J5: =IF(C5="","",C5*Premissas!$C$5*12) | K5: =IF(C5="","",(J5*(1-Premissas!$C$7)-C5*Premissas!$C$6*12-Premissas!$C$8*12)*Premissas!$C$19) | L5: =IF(C5="","",J5*Premissas!$C$20*Premissas!$C$19) | M5: =IF(C5="","",J5*Premissas!$C$21*Premissas!$C$19)
A6: Cinco clientes | B6: 5 | C6: 1500 | D6: =IF(C6="","",C6*Premissas!$C$5*(1-Premissas!$C$11)*(1-Premissas!$C$7)-C6*Premissas!$C$6-Premissas!$C$8) | E6: =IF(D6="","",D6*12) | F6: =IF(C6="","",MAX(C6*Premissas!$C$14,Premissas!$C$15)*(1-Premissas!$C$7)-C6*Premissas!$C$6-Premissas!$C$8) | G6: =IF(F6="","",F6*12) | H6: =IF(B6="","",(Premissas!$C$16+B6*Premissas!$C$17)*(1-Premissas!$C$7)) | I6: =IF(OR(G6="",H6=""),"",G6+H6) | J6: =IF(C6="","",C6*Premissas!$C$5*12) | K6: =IF(C6="","",(J6*(1-Premissas!$C$7)-C6*Premissas!$C$6*12-Premissas!$C$8*12)*Premissas!$C$19) | L6: =IF(C6="","",J6*Premissas!$C$20*Premissas!$C$19) | M6: =IF(C6="","",J6*Premissas!$C$21*Premissas!$C$19)
A7: Vinte clientes | B7: 20 | C7: 6000 | D7: =IF(C7="","",C7*Premissas!$C$5*(1-Premissas!$C$11)*(1-Premissas!$C$7)-C7*Premissas!$C$6-Premissas!$C$8) | E7: =IF(D7="","",D7*12) | F7: =IF(C7="","",MAX(C7*Premissas!$C$14,Premissas!$C$15)*(1-Premissas!$C$7)-C7*Premissas!$C$6-Premissas!$C$8) | G7: =IF(F7="","",F7*12) | H7: =IF(B7="","",(Premissas!$C$16+B7*Premissas!$C$17)*(1-Premissas!$C$7)) | I7: =IF(OR(G7="",H7=""),"",G7+H7) | J7: =IF(C7="","",C7*Premissas!$C$5*12) | K7: =IF(C7="","",(J7*(1-Premissas!$C$7)-C7*Premissas!$C$6*12-Premissas!$C$8*12)*Premissas!$C$19) | L7: =IF(C7="","",J7*Premissas!$C$20*Premissas!$C$19) | M7: =IF(C7="","",J7*Premissas!$C$21*Premissas!$C$19)
A8: Cenário livre 1 | D8: =IF(C8="","",C8*Premissas!$C$5*(1-Premissas!$C$11)*(1-Premissas!$C$7)-C8*Premissas!$C$6-Premissas!$C$8) | E8: =IF(D8="","",D8*12) | F8: =IF(C8="","",MAX(C8*Premissas!$C$14,Premissas!$C$15)*(1-Premissas!$C$7)-C8*Premissas!$C$6-Premissas!$C$8) | G8: =IF(F8="","",F8*12) | H8: =IF(B8="","",(Premissas!$C$16+B8*Premissas!$C$17)*(1-Premissas!$C$7)) | I8: =IF(OR(G8="",H8=""),"",G8+H8) | J8: =IF(C8="","",C8*Premissas!$C$5*12) | K8: =IF(C8="","",(J8*(1-Premissas!$C$7)-C8*Premissas!$C$6*12-Premissas!$C$8*12)*Premissas!$C$19) | L8: =IF(C8="","",J8*Premissas!$C$20*Premissas!$C$19) | M8: =IF(C8="","",J8*Premissas!$C$21*Premissas!$C$19)
A9: Cenário livre 2 | D9: =IF(C9="","",C9*Premissas!$C$5*(1-Premissas!$C$11)*(1-Premissas!$C$7)-C9*Premissas!$C$6-Premissas!$C$8) | E9: =IF(D9="","",D9*12) | F9: =IF(C9="","",MAX(C9*Premissas!$C$14,Premissas!$C$15)*(1-Premissas!$C$7)-C9*Premissas!$C$6-Premissas!$C$8) | G9: =IF(F9="","",F9*12) | H9: =IF(B9="","",(Premissas!$C$16+B9*Premissas!$C$17)*(1-Premissas!$C$7)) | I9: =IF(OR(G9="",H9=""),"",G9+H9) | J9: =IF(C9="","",C9*Premissas!$C$5*12) | K9: =IF(C9="","",(J9*(1-Premissas!$C$7)-C9*Premissas!$C$6*12-Premissas!$C$8*12)*Premissas!$C$19) | L9: =IF(C9="","",J9*Premissas!$C$20*Premissas!$C$19) | M9: =IF(C9="","",J9*Premissas!$C$21*Premissas!$C$19)
A11: Se a Epic quiser comprar o Zēllu de uma vez
A12: Piso | B12: =Premissas!C28
A13: Referência alta | B13: =Premissas!C29
A15: Como ler:
A16: • Canal: a Epic vende e fica com o percentual dela; você recebe o resto, paga impostos e os custos de operar.
A17: • White-label: a Epic paga a licença por colaborador (ou o mínimo mensal, o que for maior), a implantação inicial e, se combinado, uma taxa por cliente novo.
A18: • Sociedade: o lucro e o valor da empresa são divididos pela sua participação. O valor só vira dinheiro numa venda ou rodada de investimento.
A19: • Todos os números são estimativas. O piloto com um cliente real é o que vai confirmar preço, adesão e custo de IA.
